resinkit_api/.env
resinkit_api/__init__.py
resinkit_api/apps.py
resinkit_api/main.py
resinkit_api/mcp_proxy_server.py
resinkit_api/api/__init__.py
resinkit_api/api/common.py
resinkit_api/api/flink_api.py
resinkit_api/api/health.py
resinkit_api/api/pat.py
resinkit_api/api/agent/__init__.py
resinkit_api/api/agent/data_sources_api.py
resinkit_api/api/agent/db_crawl_api.py
resinkit_api/api/agent/kafka_crawl_api.py
resinkit_api/api/agent/tasks_api.py
resinkit_api/api/agent/variables_api.py
resinkit_api/api/models/__init__.py
resinkit_api/api/models/models_flink.py
resinkit_api/clients/job_manager/flink_job_manager_client.py
resinkit_api/clients/sql_gateway/flink_utils.py
resinkit_api/clients/sql_gateway/session_utils.py
resinkit_api/core/__init__.py
resinkit_api/core/config.py
resinkit_api/core/encryption.py
resinkit_api/core/find_root.py
resinkit_api/core/flink_options.py
resinkit_api/core/logging.py
resinkit_api/db/__init__.py
resinkit_api/db/alembic.ini
resinkit_api/db/data_sources_crud.py
resinkit_api/db/database.py
resinkit_api/db/models.py
resinkit_api/db/tasks_crud.py
resinkit_api/db/variables_crud.py
resinkit_api/db/alembic/README
resinkit_api/db/alembic/env.py
resinkit_api/db/alembic/script.py.mako
resinkit_api/db/alembic/versions/.gitkeep
resinkit_api/db/alembic/versions/32c843eb8225_add_task_expiry.py
resinkit_api/db/alembic/versions/7199cc0f9e6c_make_data_source_connection_fields_.py
resinkit_api/db/alembic/versions/a261d8461fde_rename_sql_sources_to_data_sources.py
resinkit_api/db/alembic/versions/a53a22092259_create_initial_tables.py
resinkit_api/db/alembic/versions/adfa6c905b9d_add_task_expiry.py
resinkit_api/db/alembic/versions/b8c1bd22cb20_add_sql_sources_table.py
resinkit_api/dependencies/data_sources.py
resinkit_api/mcp/agent/mcp_data_explorer.py
resinkit_api/mcp/agent/mcp_prompts.py
resinkit_api/mcp/agent/mcp_resources.py
resinkit_api/services/__init__.py
resinkit_api/services/flink_session_service.py
resinkit_api_python-0.1.4.dist-info/METADATA
resinkit_api_python-0.1.4.dist-info/WHEEL
resinkit_api_python-0.1.4.dist-info/RECORD
